zenodo_api/__init__.py
zenodo_api/cli.py
zenodo_api/new_version.py
zenodo_api/retrieve.py
zenodo_api/upload_files.py
zenodo_api/url_selector.py
zenodo_api-1.0.0.dist-info/entry_points.txt
zenodo_api-1.0.0.dist-info/licenses/LICENSE
zenodo_api-1.0.0.dist-info/WHEEL
zenodo_api-1.0.0.dist-info/METADATA
zenodo_api-1.0.0.dist-info/RECORD
