Metadata-Version: 2.4
Name: zenodo_api
Version: 1.0.0
Summary: Wrapper for Zenodo API
Home-page: https://github.com/IslasGECI/zenodo_api
Author: Ciencia de Datos • GECI
Author-email: ciencia.datos@islas.org.mx
Requires-Python: >=3.9
Classifier: License :: OSI Approved :: GNU General Public License v3 or later (GPLv3+)
License-File: LICENSE
Requires-Dist: requests
Requires-Dist: typer[all]
Requires-Dist: click<8.2.0
